abril/__init__.py
abril/clip_compare.py
abril/core.py
abril-0.1.9.dist-info/LICENSE
abril-0.1.9.dist-info/METADATA
abril-0.1.9.dist-info/WHEEL
abril-0.1.9.dist-info/dependency_links.txt
abril-0.1.9.dist-info/top_level.txt
abril-0.1.9.dist-info/RECORD
