Metadata-Version: 2.1
Name: abril
Version: 0.1.9
Summary: A library for comparing text and images using CLIP
Author-email: Luis Rico <beborico16@gmail.com>
License: MIT
Project-URL: Homepage, https://github.com/yourusername/abril
Requires-Python: >=3.7
License-File: LICENSE
Requires-Dist: torch>=1.7.1
Requires-Dist: pillow>=7.1.2
Requires-Dist: numpy>=1.18.5
